involute/__init__.py
zen_involute-1.0.3.dist-info/METADATA
zen_involute-1.0.3.dist-info/WHEEL
zen_involute-1.0.3.dist-info/top_level.txt
zen_involute-1.0.3.dist-info/RECORD
