Metadata-Version: 2.1
Name: zen-involute
Version: 1.0.3
Summary: Involute gear profile builder for ZenCAD
Home-page: https://gitlab.com/hnau_zen/involute
Author: Mark Zorikhin
Author-email: hnau256@gmail.com
License: UNKNOWN
Platform: UNKNOWN
Classifier: Programming Language :: Python :: 3
Classifier: License :: OSI Approved :: MIT License
Classifier: Operating System :: OS Independent
Requires-Python: >=3.6
